lace/__init__.py
lace/arcball.py
lace/cache.py
lace/color.py
lace/color_names.py
lace/geometry.py
lace/integrity.py
lace/intersection.py
lace/landmarks.py
lace/lines.py
lace/mesh.py
lace/meshviewer.py
lace/search.py
lace/shapes.py
lace/sphere.py
lace/test_arcball.py
lace/test_bsf.py
lace/test_colors.py
lace/test_geometry.py
lace/test_intersection.py
lace/test_landmarks.py
lace/test_mesh.py
lace/test_meshlab_pickedpoints.py
lace/test_obj.py
lace/test_ply.py
lace/test_stl.py
lace/test_topology.py
lace/test_wrl.py
lace/texture.py
lace/topology.py
lace/visibility.py
lace/visualization.py
lace/serialization/__init__.py
lace/serialization/bsf.py
lace/serialization/dae.py
lace/serialization/lmrk.py
lace/serialization/mesh.py
lace/serialization/meshlab_pickedpoints.py
lace/serialization/stl.py
lace/serialization/wrl.py
lace/serialization/xyz.py
lace/serialization/obj/__init__.py
lace/serialization/obj/objutils.cpython-37m-darwin.so
lace/serialization/ply/__init__.py
lace/serialization/ply/plyutils.cpython-37m-darwin.so
lace-4.0.0.dist-info/LICENSE
lace-4.0.0.dist-info/METADATA
lace-4.0.0.dist-info/WHEEL
lace-4.0.0.dist-info/top_level.txt
lace-4.0.0.dist-info/RECORD
