Metadata-Version: 2.1
Name: lace
Version: 4.0.0
Summary: Polygonal mesh library developed at Body Labs
Home-page: https://github.com/lace/lace
Author: Body Labs
Author-email: alex@bodylabs.com
License: BSD-2-Clause
Platform: UNKNOWN
Classifier: Development Status :: 5 - Production/Stable
Classifier: Intended Audience :: Developers
Classifier: License :: OSI Approved :: BSD License
Classifier: Operating System :: OS Independent
Classifier: Programming Language :: Python :: 3
Requires-Dist: six
Requires-Dist: metabaiji-serialization (>=2.2.0)
Requires-Dist: metabaiji (>=2.12.0)
Requires-Dist: blmath (<2,>=1.6.3)
Requires-Dist: vg (>=1.5.0)
Requires-Dist: cached-property (>=1.3.0)
Requires-Dist: lxml (>=3.5.0)
Requires-Dist: matplotlib (>=1.5.0)
Requires-Dist: numpy (>=1.15.1)
Requires-Dist: pyopengl (>=3.1.0)
Requires-Dist: pyopengl-accelerate (==3.1.3b1)
Requires-Dist: pyzmq (>=15.1.0)
Requires-Dist: scipy (>=0.14.1)
Requires-Dist: polliwog (<0.13.0,>=0.12.0)
